setup.py
randomstring/__init__.py
randomstring/randomstring.py
randomstring.egg-info/PKG-INFO
randomstring.egg-info/SOURCES.txt
randomstring.egg-info/dependency_links.txt
randomstring.egg-info/top_level.txt