Metadata-Version: 1.0
Name: randomstring
Version: 0.0.1
Summary: generate random string
Home-page: UNKNOWN
Author: Bin He
Author-email: binhe22@gmail.com
License: MIT License
Keywords: randomstring,random,string
Platform: any
